baralho_py/__init__.py
baralho_py/baralho.py
baralho_py/main.py
baralho_py-0.2.1.dist-info/METADATA
baralho_py-0.2.1.dist-info/WHEEL
baralho_py-0.2.1.dist-info/entry_points.txt
baralho_py-0.2.1.dist-info/top_level.txt
baralho_py-0.2.1.dist-info/RECORD
