Metadata-Version: 2.1
Name: baralho-py
Version: 0.2.1
Summary: Jogo simples de batalha.
Home-page: https://github.com/arthurfaraujo/ed
Author: Arthur Felipe
Author-email: arthurfelipe5567@gmail.com
Classifier: Programming Language :: Python :: 3
Classifier: License :: OSI Approved :: MIT License
Classifier: Operating System :: OS Independent
Requires-Python: >=3.6
